xlsx2xlsm/__init__.py
xlsx2xlsm/xlsx2xlsm.py
xlsx2xlsm-1.6.dist-info/METADATA
xlsx2xlsm-1.6.dist-info/WHEEL
xlsx2xlsm-1.6.dist-info/top_level.txt
xlsx2xlsm-1.6.dist-info/RECORD
