Metadata-Version: 2.1
Name: xlsx2xlsm
Version: 1.6
Summary: This package is used to convert xlsx files to xlsm files and supports custom macros
Home-page: https://github.com/caozhui/xlsx2xlsm
Author: Zhui Cao
Author-email: 857330385@qq.com
Keywords: xlsx,xlsx2xlsm,xlsm,xlsxtoxlsm,xlsx-to-xlsm,xlsx-xlsm
